densitypeakclustering/__init__.py
densitypeakclustering/densitypeakclustering.py
densitypeakclustering-1.0.1.dist-info/LICENSE
densitypeakclustering-1.0.1.dist-info/METADATA
densitypeakclustering-1.0.1.dist-info/WHEEL
densitypeakclustering-1.0.1.dist-info/top_level.txt
densitypeakclustering-1.0.1.dist-info/RECORD
