Metadata-Version: 2.1
Name: densitypeakclustering
Version: 1.0.1
Summary: Implementation of the Clustering by fast search and find of density peaks algorithm
Home-page: https://github.com/pgoltstein/densitypeakclustering
Author: Pieter Goltstein
Author-email: xpieter@mac.com
Classifier: Development Status :: 4 - Beta
Classifier: Intended Audience :: Science/Research
Classifier: License :: OSI Approved :: GNU General Public License v3 (GPLv3)
Classifier: Programming Language :: Python :: 3
Classifier: Topic :: Scientific/Engineering
Requires-Python: >=3.6
License-File: LICENSE
Requires-Dist: numpy
Requires-Dist: scikit-learn
Requires-Dist: matplotlib
